{"data":{"_id":17000,"properties":{"lease":{"name":"lease","kind":"m:1","cascade":["persist"],"entity":"Lease","type":"Lease","owner":true,"createForeignKeyConstraint":true,"array":false,"runtimeType":"Lease"},"noticeDate":{"name":"noticeDate","kind":"scalar","type":"date","getter":false,"setter":false,"array":false,"runtimeType":"Date"},"plannedExitDate":{"name":"plannedExitDate","kind":"scalar","type":"date","getter":false,"setter":false,"array":false,"runtimeType":"Date"},"reason":{"name":"reason","kind":"scalar","type":"text","nullable":true,"getter":false,"setter":false,"array":false,"optional":true,"runtimeType":"string"},"mutualAgreement":{"name":"mutualAgreement","kind":"scalar","type":"boolean","default":false,"getter":false,"setter":false,"array":false,"runtimeType":"boolean"},"penaltyAmount":{"name":"penaltyAmount","kind":"scalar","type":"number","nullable":true,"getter":false,"setter":false,"array":false,"optional":true,"runtimeType":"number"},"penaltyWaived":{"name":"penaltyWaived","kind":"scalar","type":"boolean","default":false,"getter":false,"setter":false,"array":false,"runtimeType":"boolean"},"status":{"name":"status","kind":"scalar","enum":true,"items":["PENDING","CONFIRMED","CANCELLED"],"type":"string","default":"PENDING","array":false,"runtimeType":"ExitNoticeStatus"}},"primaryKeys":[],"filters":{},"hooks":{},"indexes":[],"uniques":[],"className":"ExitNotice","path":"./src/features/leases/entities/ExitNotice.ts","collection":"exit_notices","name":"ExitNotice","abstract":false,"internal":true,"constructorParams":["partial"],"toJsonParams":[],"extends":"BaseTenantEntity","useCache":true},"origin":"./src/features/leases/entities/ExitNotice.ts","hash":"05a185f77047128888a85195fc350249","version":"6.6.3"}
